{
  "0": {
    "Data": "Success",
    "time": 125.0087821483612,
    "mqNum": 830,
    "eqNum": 53,
    "testNum": 18799,
    "passingRate": 0.9996276397680728
  },
  "1": {
    "Data": "Success",
    "time": 372.25043296813965,
    "mqNum": 1577,
    "eqNum": 85,
    "testNum": 38015,
    "passingRate": 0.9989214783638037
  },
  "2": {
    "Data": "Success",
    "time": 177.7772181034088,
    "mqNum": 1000,
    "eqNum": 70,
    "testNum": 24481,
    "passingRate": 0.9995506719496753
  },
  "3": {
    "Data": "Success",
    "time": 227.71103286743164,
    "mqNum": 1376,
    "eqNum": 74,
    "testNum": 28812,
    "passingRate": 0.999757045675413
  },
  "4": {
    "Data": "Success",
    "time": 127.40691184997559,
    "mqNum": 773,
    "eqNum": 50,
    "testNum": 11429,
    "passingRate": 0.9987750459357774
  },
  "5": {
    "Data": "Success",
    "time": 162.55295991897583,
    "mqNum": 921,
    "eqNum": 60,
    "testNum": 16939,
    "passingRate": 0.9989963988429069
  },
  "6": {
    "Data": "Success",
    "time": 118.30160117149353,
    "mqNum": 918,
    "eqNum": 67,
    "testNum": 21914,
    "passingRate": 0.9989048097106872
  },
  "7": {
    "Data": "Success",
    "time": 96.27023386955261,
    "mqNum": 611,
    "eqNum": 53,
    "testNum": 12301,
    "passingRate": 0.9995122347776604
  },
  "8": {
    "Data": "Success",
    "time": 187.25539088249207,
    "mqNum": 1235,
    "eqNum": 63,
    "testNum": 23146,
    "passingRate": 0.9998841144022621
  },
  "9": {
    "Data": "Success",
    "time": 50.26297879219055,
    "mqNum": 436,
    "eqNum": 47,
    "testNum": 13379,
    "passingRate": 1.0
  }
}